LICENSE
MANIFEST.in
README.md
pyproject.toml
setup.cfg
setup.py
../CMakeLists.txt
b12od/__init__.py
b12od/b12od.c
b12od/b12od.pyx
b12od-core/CMakeLists.txt
b12od-core/include/b12od/bebuf.h
b12od-core/include/b12od/bech32_decode.h
b12od-core/include/b12od/bigsize.h
b12od-core/include/b12od/bolt12_decode.h
b12od-core/include/b12od/bolt12_json.h
b12od-core/include/b12od/bolt12_json_tlv.h
b12od-core/include/b12od/bolt12_offer_decode.h
b12od-core/include/b12od/bolt12_offer_json.h
b12od-core/include/b12od/bolt12_tlv_field_check.h
b12od-core/include/b12od/bolt12_types.h
b12od-core/include/b12od/hex_enc.h
b12od-core/include/b12od/json_encode.h
b12od-core/include/b12od/math_utils.h
b12od-core/include/b12od/safe_char.h
b12od-core/include/b12od/tlv.h
b12od-core/include/b12od/tlv_field_check.h
b12od-core/include/b12od/tobytesbuf.h
b12od-core/src/bin/b12od.c
b12od-core/src/bin/b12od_cmp.c
b12od-core/src/bin/b12od_many.c
b12od-core/src/lib/bech32_decode.c
b12od-core/src/lib/bigsize.c
b12od-core/src/lib/bolt12_decode.c
b12od-core/src/lib/bolt12_json.c
b12od-core/src/lib/bolt12_json_tlv.c
b12od-core/src/lib/bolt12_offer_decode.c
b12od-core/src/lib/bolt12_offer_json.c
b12od-core/src/lib/bolt12_tlv_field_check.c
b12od-core/src/lib/hex_enc.c
b12od-core/src/lib/safe_char.c
b12od-core/src/lib/tlv.c
b12od-core/tests/offer_tests.txt
b12od.egg-info/PKG-INFO
b12od.egg-info/SOURCES.txt
b12od.egg-info/dependency_links.txt
b12od.egg-info/not-zip-safe
b12od.egg-info/requires.txt
b12od.egg-info/top_level.txt
tests/test_offer_decode.py