Metadata-Version: 2.4
Name: b12od
Version: 0.1.1
Summary: Python bindings for b12od C library
Home-page: https://github.com/21M4TW/b12od
Author: 21M4TW
Author-email: 21M4TW@proton.me
License: "BSD 2-Clause"
Classifier: Programming Language :: Python :: 3
Classifier: Programming Language :: C
Classifier: Programming Language :: Cython
Classifier: Operating System :: OS Independent
Requires-Python: >=3.7
License-File: LICENSE
Requires-Dist: pytest
Dynamic: license-file
Dynamic: requires-dist
